minipages/__init__.py
minipages/admin.py
minipages/apps.py
minipages/models.py
minipages/urls.py
minipages/views.py
minipages/locale/en/LC_MESSAGES/django.mo
minipages/locale/en/LC_MESSAGES/django.po
minipages/locale/fr/LC_MESSAGES/django.mo
minipages/locale/fr/LC_MESSAGES/django.po
minipages/migrations/0001_initial.py
minipages/migrations/__init__.py
minipages/templates/minipages/page_detail.html
minipages/templates/minipages/page_list.html
django_minipages-0.1.0.dist-info/LICENSE
django_minipages-0.1.0.dist-info/METADATA
django_minipages-0.1.0.dist-info/NOTICE
django_minipages-0.1.0.dist-info/WHEEL
django_minipages-0.1.0.dist-info/top_level.txt
django_minipages-0.1.0.dist-info/RECORD
